LICENSE
lightwait/__init__.py
lightwait/cli.py
lightwait/exception.py
lightwait/lightwait.ini
lightwait/lightwait.py
lightwait/template/base.index
lightwait/template/main.index
lightwait/template/post.index
lightwait/template/tag.index
lightwait/www/css/main.css
lightwait/www/image/favicon.ico
lightwait-0.0.4.1.dist-info/entry_points.txt
lightwait-0.0.4.1.dist-info/LICENSE
lightwait-0.0.4.1.dist-info/WHEEL
lightwait-0.0.4.1.dist-info/METADATA
lightwait-0.0.4.1.dist-info/RECORD
