Metadata-Version: 2.1
Name: lightwait
Version: 0.0.4.1
Summary: Light-wait produces the bare minimum blog content from markdown files
Home-page: https://github.com/mechregard/light-wait
License: CC0 1.0 Universal
Keywords: blog,markdown
Author: dlange
Requires-Python: >=3.8,<4.0
Classifier: Environment :: Console
Classifier: License :: CC0 1.0 Universal (CC0 1.0) Public Domain Dedication
Classifier: License :: Other/Proprietary License
Classifier: Operating System :: OS Independent
Classifier: Programming Language :: Python :: 3
Classifier: Programming Language :: Python :: 3.10
Classifier: Programming Language :: Python :: 3.8
Classifier: Programming Language :: Python :: 3.9
Classifier: Topic :: Internet :: WWW/HTTP :: Dynamic Content
Classifier: Topic :: Text Processing :: Markup :: Markdown
Requires-Dist: Jinja2 (>=3.1.2,<4.0.0)
Requires-Dist: Markdown (>=3.3.7,<4.0.0)
Requires-Dist: click (>=8.1.3,<9.0.0)
Requires-Dist: feedgen (>=0.9.0,<0.10.0)
Requires-Dist: pathvalidate (>=2.5.0,<3.0.0)
Project-URL: Repository, https://github.com/mechregard/light-wait
